{
  "Code": "TGSAS",
  "Name": "TGS DIŞ TİCARET A.Ş.",
  "City": "İSTANBUL",
  "IndependentAuditingFirm": "ULUSLARARASI BAĞIMSIZ DENETİM A.Ş.",
  "Data": {
    "Revenue": 12542092.0,
    "CostOfRevenue": -55488.0,
    "OperatingProfit": 0.0,
    "GrossProfit": 12486604.0,
    "NetProfit": 3286930.0,
    "OperatingExpenses": {
      "ManagementExpenses": -8243543.0,
      "MarketingExpenses": -29557.0,
      "RD_Expenses": 0.0,
      "OtherExpenses": -1404204.0
    },
    "Tax": {
      "Tax1": -722852.0,
      "Tax2": -403329.0
    },
    "Amortization": 170732.0,
    "Ratios": {
      "GrossMargin": 0.0,
      "OperatingMargin": 0.0,
      "ReturnOnAssets": 0.0,
      "ReturnOnEquity": 0.0
    }
  },
  "xlsFile": "C:\\Users\\SnorlaX\\Downloads\\Yeni klasör\\Capstone\\data/Upload/TGS DIŞ TİCARET A.Ş.(15.05.2023).xlsx"
}
